{"trial_id": "0178", "hyperparameters": {"space": [{"class_name": "Choice", "config": {"name": "activation", "default": "relu", "conditions": [], "values": ["relu", "tanh"], "ordered": false}}, {"class_name": "Int", "config": {"name": "first_units", "default": null, "conditions": [], "min_value": 10, "max_value": 100, "step": 1, "sampling": "linear"}}, {"class_name": "Int", "config": {"name": "num_layers", "default": null, "conditions": [], "min_value": 2, "max_value": 7, "step": 1, "sampling": "linear"}}, {"class_name": "Int", "config": {"name": "units_0", "default": null, "conditions": [], "min_value": 10, "max_value": 100, "step": 1, "sampling": "linear"}}, {"class_name": "Int", "config": {"name": "units_1", "default": null, "conditions": [], "min_value": 10, "max_value": 100, "step": 1, "sampling": "linear"}}, {"class_name": "Int", "config": {"name": "units_2", "default": null, "conditions": [], "min_value": 10, "max_value": 100, "step": 1, "sampling": "linear"}}, {"class_name": "Int", "config": {"name": "units_3", "default": null, "conditions": [], "min_value": 10, "max_value": 100, "step": 1, "sampling": "linear"}}, {"class_name": "Int", "config": {"name": "units_4", "default": null, "conditions": [], "min_value": 10, "max_value": 100, "step": 1, "sampling": "linear"}}, {"class_name": "Int", "config": {"name": "units_5", "default": null, "conditions": [], "min_value": 10, "max_value": 100, "step": 1, "sampling": "linear"}}, {"class_name": "Int", "config": {"name": "units_6", "default": null, "conditions": [], "min_value": 10, "max_value": 100, "step": 1, "sampling": "linear"}}], "values": {"activation": "tanh", "first_units": 37, "num_layers": 5, "units_0": 24, "units_1": 14, "units_2": 57, "units_3": 93, "units_4": 16, "units_5": 98, "units_6": 77, "tuner/epochs": 4, "tuner/initial_epoch": 0, "tuner/bracket": 3, "tuner/round": 0}}, "metrics": {"metrics": {"accuracy": {"direction": "max", "observations": [{"value": [0.7294355630874634], "step": 1}]}, "loss": {"direction": "min", "observations": [{"value": [0.5576911568641663], "step": 1}]}, "val_accuracy": {"direction": "max", "observations": [{"value": [0.7304956316947937], "step": 1}]}, "val_loss": {"direction": "min", "observations": [{"value": [0.5584765672683716], "step": 1}]}}}, "score": 0.7304956316947937, "best_step": 1, "status": "COMPLETED", "message": null}