{"trial_id": "0407", "hyperparameters": {"space": [{"class_name": "Choice", "config": {"name": "activation", "default": "relu", "conditions": [], "values": ["relu", "tanh"], "ordered": false}}, {"class_name": "Int", "config": {"name": "first_units", "default": null, "conditions": [], "min_value": 10, "max_value": 100, "step": 1, "sampling": "linear"}}, {"class_name": "Int", "config": {"name": "num_layers", "default": null, "conditions": [], "min_value": 2, "max_value": 7, "step": 1, "sampling": "linear"}}, {"class_name": "Int", "config": {"name": "units_0", "default": null, "conditions": [], "min_value": 10, "max_value": 100, "step": 1, "sampling": "linear"}}, {"class_name": "Int", "config": {"name": "units_1", "default": null, "conditions": [], "min_value": 10, "max_value": 100, "step": 1, "sampling": "linear"}}, {"class_name": "Int", "config": {"name": "units_2", "default": null, "conditions": [], "min_value": 10, "max_value": 100, "step": 1, "sampling": "linear"}}, {"class_name": "Int", "config": {"name": "units_3", "default": null, "conditions": [], "min_value": 10, "max_value": 100, "step": 1, "sampling": "linear"}}, {"class_name": "Int", "config": {"name": "units_4", "default": null, "conditions": [], "min_value": 10, "max_value": 100, "step": 1, "sampling": "linear"}}, {"class_name": "Int", "config": {"name": "units_5", "default": null, "conditions": [], "min_value": 10, "max_value": 100, "step": 1, "sampling": "linear"}}, {"class_name": "Int", "config": {"name": "units_6", "default": null, "conditions": [], "min_value": 10, "max_value": 100, "step": 1, "sampling": "linear"}}], "values": {"activation": "tanh", "first_units": 100, "num_layers": 4, "units_0": 89, "units_1": 65, "units_2": 14, "units_3": 16, "units_4": 83, "units_5": 32, "units_6": 43, "tuner/epochs": 4, "tuner/initial_epoch": 0, "tuner/bracket": 3, "tuner/round": 0}}, "metrics": {"metrics": {"accuracy": {"direction": "max", "observations": [{"value": [0.7321956157684326], "step": 3}]}, "loss": {"direction": "min", "observations": [{"value": [0.5513465404510498], "step": 3}]}, "val_accuracy": {"direction": "max", "observations": [{"value": [0.7285131216049194], "step": 3}]}, "val_loss": {"direction": "min", "observations": [{"value": [0.5554032325744629], "step": 3}]}}}, "score": 0.7285131216049194, "best_step": 3, "status": "COMPLETED", "message": null}