{"trial_id": "0114", "hyperparameters": {"space": [{"class_name": "Choice", "config": {"name": "activation", "default": "relu", "conditions": [], "values": ["relu", "tanh"], "ordered": false}}, {"class_name": "Int", "config": {"name": "first_units", "default": null, "conditions": [], "min_value": 10, "max_value": 100, "step": 1, "sampling": "linear"}}, {"class_name": "Int", "config": {"name": "num_layers", "default": null, "conditions": [], "min_value": 2, "max_value": 7, "step": 1, "sampling": "linear"}}, {"class_name": "Int", "config": {"name": "units_0", "default": null, "conditions": [], "min_value": 10, "max_value": 100, "step": 1, "sampling": "linear"}}, {"class_name": "Int", "config": {"name": "units_1", "default": null, "conditions": [], "min_value": 10, "max_value": 100, "step": 1, "sampling": "linear"}}, {"class_name": "Int", "config": {"name": "units_2", "default": null, "conditions": [], "min_value": 10, "max_value": 100, "step": 1, "sampling": "linear"}}, {"class_name": "Int", "config": {"name": "units_3", "default": null, "conditions": [], "min_value": 10, "max_value": 100, "step": 1, "sampling": "linear"}}, {"class_name": "Int", "config": {"name": "units_4", "default": null, "conditions": [], "min_value": 10, "max_value": 100, "step": 1, "sampling": "linear"}}, {"class_name": "Int", "config": {"name": "units_5", "default": null, "conditions": [], "min_value": 10, "max_value": 100, "step": 1, "sampling": "linear"}}, {"class_name": "Int", "config": {"name": "units_6", "default": null, "conditions": [], "min_value": 10, "max_value": 100, "step": 1, "sampling": "linear"}}], "values": {"activation": "relu", "first_units": 83, "num_layers": 5, "units_0": 24, "units_1": 68, "units_2": 93, "units_3": 46, "units_4": 18, "units_5": 98, "units_6": 21, "tuner/epochs": 4, "tuner/initial_epoch": 2, "tuner/bracket": 4, "tuner/round": 1, "tuner/trial_id": "0097"}}, "metrics": {"metrics": {"accuracy": {"direction": "max", "observations": [{"value": [0.7314958572387695], "step": 1}]}, "loss": {"direction": "min", "observations": [{"value": [0.5518701076507568], "step": 1}]}, "val_accuracy": {"direction": "max", "observations": [{"value": [0.7281632423400879], "step": 1}]}, "val_loss": {"direction": "min", "observations": [{"value": [0.5539739727973938], "step": 1}]}}}, "score": 0.7281632423400879, "best_step": 1, "status": "COMPLETED", "message": null}